{
    "attributes": {
        "controlGroupInput": {
            "chainingSystem": "HIERARCHICAL",
            "controlStyle": "oneLine",
            "ignoreParentSettingsJSON": {
                "ignoreFilters": false,
                "ignoreQuery": false,
                "ignoreTimerange": false,
                "ignoreValidations": false
            },
            "panelsJSON": {
                "b6299f3c-17e7-4663-8a63-3c856c683ea8": {
                    "explicitInput": {
                        "enhancements": {},
                        "fieldName": "observer.ip",
                        "grow": false,
                        "id": "b6299f3c-17e7-4663-8a63-3c856c683ea8",
                        "searchTechnique": "prefix",
                        "selectedOptions": [
                            "10.200.99.13"
                        ],
                        "title": "observer.ip",
                        "width": "medium"
                    },
                    "grow": false,
                    "order": 0,
                    "type": "optionsListControl",
                    "width": "medium"
                }
            },
            "showApplySelections": false
        },
        "description": "",
        "kibanaSavedObjectMeta": {
            "searchSourceJSON": {
                "filter": [
                    {
                        "$state": {
                            "store": "appState"
                        },
                        "meta": {
                            "alias": null,
                            "disabled": false,
                            "field": "event.dataset",
                            "indexRefName": "kibanaSavedObjectMeta.searchSourceJSON.filter[0].meta.index",
                            "key": "event.dataset",
                            "negate": false,
                            "params": {
                                "query": "panw_metrics.system"
                            },
                            "type": "phrase"
                        },
                        "query": {
                            "match_phrase": {
                                "event.dataset": "panw_metrics.system"
                            }
                        }
                    }
                ],
                "query": {
                    "language": "kuery",
                    "query": ""
                }
            }
        },
        "optionsJSON": {
            "hidePanelTitles": false,
            "syncColors": false,
            "syncCursor": true,
            "syncTooltips": false,
            "useMargins": true
        },
        "panelsJSON": [
            {
                "embeddableConfig": {
                    "attributes": {
                        "references": [
                            {
                                "id": "metrics-*",
                                "name": "indexpattern-datasource-layer-84d94cdf-99fe-43f4-b520-8343a94355b6",
                                "type": "index-pattern"
                            }
                        ],
                        "state": {
                            "adHocDataViews": {},
                            "datasourceStates": {
                                "formBased": {
                                    "layers": {
                                        "84d94cdf-99fe-43f4-b520-8343a94355b6": {
                                            "columnOrder": [
                                                "6c356040-3aaf-4d3f-abb5-131eec233680",
                                                "799e8f5f-8751-41aa-af71-55e5b61fa89e",
                                                "9b2e8a4f-81f2-486c-a4e0-9219e35303e3"
                                            ],
                                            "columns": {
                                                "6c356040-3aaf-4d3f-abb5-131eec233680": {
                                                    "customLabel": true,
                                                    "dataType": "number",
                                                    "filter": {
                                                        "language": "kuery",
                                                        "query": "\"panw.system.uptime.days\": *"
                                                    },
                                                    "isBucketed": false,
                                                    "label": "Days",
                                                    "operationType": "last_value",
                                                    "params": {
                                                        "sortField": "@timestamp"
                                                    },
                                                    "scale": "ratio",
                                                    "sourceField": "panw.system.uptime.days"
                                                },
                                                "799e8f5f-8751-41aa-af71-55e5b61fa89e": {
                                                    "customLabel": true,
                                                    "dataType": "number",
                                                    "filter": {
                                                        "language": "kuery",
                                                        "query": "\"panw.system.uptime.hours\": *"
                                                    },
                                                    "isBucketed": false,
                                                    "label": "Hours",
                                                    "operationType": "last_value",
                                                    "params": {
                                                        "sortField": "@timestamp"
                                                    },
                                                    "scale": "ratio",
                                                    "sourceField": "panw.system.uptime.hours"
                                                },
                                                "9b2e8a4f-81f2-486c-a4e0-9219e35303e3": {
                                                    "customLabel": true,
                                                    "dataType": "number",
                                                    "filter": {
                                                        "language": "kuery",
                                                        "query": "\"panw.system.uptime.minutes\": *"
                                                    },
                                                    "isBucketed": false,
                                                    "label": "Minutes",
                                                    "operationType": "last_value",
                                                    "params": {
                                                        "sortField": "@timestamp"
                                                    },
                                                    "scale": "ratio",
                                                    "sourceField": "panw.system.uptime.minutes"
                                                }
                                            },
                                            "incompleteColumns": {},
                                            "sampling": 1
                                        }
                                    }
                                },
                                "indexpattern": {
                                    "layers": {}
                                },
                                "textBased": {
                                    "layers": {}
                                }
                            },
                            "filters": [],
                            "internalReferences": [],
                            "query": {
                                "language": "kuery",
                                "query": ""
                            },
                            "visualization": {
                                "columns": [
                                    {
                                        "columnId": "6c356040-3aaf-4d3f-abb5-131eec233680",
                                        "isTransposed": false
                                    },
                                    {
                                        "columnId": "799e8f5f-8751-41aa-af71-55e5b61fa89e",
                                        "isTransposed": false
                                    },
                                    {
                                        "columnId": "9b2e8a4f-81f2-486c-a4e0-9219e35303e3",
                                        "isTransposed": false
                                    }
                                ],
                                "layerId": "84d94cdf-99fe-43f4-b520-8343a94355b6",
                                "layerType": "data"
                            }
                        },
                        "title": "",
                        "type": "lens",
                        "visualizationType": "lnsDatatable"
                    },
                    "enhancements": {}
                },
                "gridData": {
                    "h": 6,
                    "i": "19dc313f-122c-4589-9cb4-f2ee8a306aeb",
                    "w": 11,
                    "x": 0,
                    "y": 0
                },
                "panelIndex": "19dc313f-122c-4589-9cb4-f2ee8a306aeb",
                "title": "Up Time",
                "type": "lens"
            },
            {
                "embeddableConfig": {
                    "attributes": {
                        "references": [
                            {
                                "id": "metrics-*",
                                "name": "indexpattern-datasource-layer-ef579182-b6a5-4392-a32e-2cc104fed1ef",
                                "type": "index-pattern"
                            }
                        ],
                        "state": {
                            "adHocDataViews": {},
                            "datasourceStates": {
                                "formBased": {
                                    "layers": {
                                        "ef579182-b6a5-4392-a32e-2cc104fed1ef": {
                                            "columnOrder": [
                                                "905a04aa-1710-4cb4-bf5a-d2b312177d55",
                                                "deb6ef95-c478-4813-b0d9-69e4a25385d5",
                                                "de5c6831-fb44-488c-a2d0-1c9168f51317",
                                                "65c51155-3397-479c-ae16-1d5f92b497c9",
                                                "437b6d5b-4b0a-466e-8d6b-02f5e7c6a146",
                                                "951b20c4-dd2b-4ec1-be9b-eff9a2c107e5",
                                                "8f8e0e79-3e25-4cba-abf7-a4887722b403",
                                                "f7a662cc-3b57-49cf-9dad-f72d1d79fd64"
                                            ],
                                            "columns": {
                                                "437b6d5b-4b0a-466e-8d6b-02f5e7c6a146": {
                                                    "customLabel": true,
                                                    "dataType": "number",
                                                    "filter": {
                                                        "language": "kuery",
                                                        "query": "\"panw.system.cpu.wait\": *"
                                                    },
                                                    "isBucketed": false,
                                                    "label": "Wait",
                                                    "operationType": "last_value",
                                                    "params": {
                                                        "sortField": "@timestamp"
                                                    },
                                                    "scale": "ratio",
                                                    "sourceField": "panw.system.cpu.wait"
                                                },
                                                "65c51155-3397-479c-ae16-1d5f92b497c9": {
                                                    "customLabel": true,
                                                    "dataType": "number",
                                                    "filter": {
                                                        "language": "kuery",
                                                        "query": "\"panw.system.cpu.idle\": *"
                                                    },
                                                    "isBucketed": false,
                                                    "label": "Idle",
                                                    "operationType": "last_value",
                                                    "params": {
                                                        "sortField": "@timestamp"
                                                    },
                                                    "scale": "ratio",
                                                    "sourceField": "panw.system.cpu.idle"
                                                },
                                                "8f8e0e79-3e25-4cba-abf7-a4887722b403": {
                                                    "customLabel": true,
                                                    "dataType": "number",
                                                    "filter": {
                                                        "language": "kuery",
                                                        "query": "\"panw.system.cpu.system_int\": *"
                                                    },
                                                    "isBucketed": false,
                                                    "label": "System Interrupt",
                                                    "operationType": "last_value",
                                                    "params": {
                                                        "sortField": "@timestamp"
                                                    },
                                                    "scale": "ratio",
                                                    "sourceField": "panw.system.cpu.system_int"
                                                },
                                                "905a04aa-1710-4cb4-bf5a-d2b312177d55": {
                                                    "customLabel": true,
                                                    "dataType": "number",
                                                    "filter": {
                                                        "language": "kuery",
                                                        "query": "\"panw.system.cpu.user\": *"
                                                    },
                                                    "isBucketed": false,
                                                    "label": "User",
                                                    "operationType": "last_value",
                                                    "params": {
                                                        "sortField": "@timestamp"
                                                    },
                                                    "scale": "ratio",
                                                    "sourceField": "panw.system.cpu.user"
                                                },
                                                "951b20c4-dd2b-4ec1-be9b-eff9a2c107e5": {
                                                    "customLabel": true,
                                                    "dataType": "number",
                                                    "filter": {
                                                        "language": "kuery",
                                                        "query": "\"panw.system.cpu.hi\": *"
                                                    },
                                                    "isBucketed": false,
                                                    "label": "HW Interrupt",
                                                    "operationType": "last_value",
                                                    "params": {
                                                        "sortField": "@timestamp"
                                                    },
                                                    "scale": "ratio",
                                                    "sourceField": "panw.system.cpu.hi"
                                                },
                                                "de5c6831-fb44-488c-a2d0-1c9168f51317": {
                                                    "customLabel": true,
                                                    "dataType": "number",
                                                    "filter": {
                                                        "language": "kuery",
                                                        "query": "\"panw.system.cpu.nice\": *"
                                                    },
                                                    "isBucketed": false,
                                                    "label": "Nice",
                                                    "operationType": "last_value",
                                                    "params": {
                                                        "sortField": "@timestamp"
                                                    },
                                                    "scale": "ratio",
                                                    "sourceField": "panw.system.cpu.nice"
                                                },
                                                "deb6ef95-c478-4813-b0d9-69e4a25385d5": {
                                                    "customLabel": true,
                                                    "dataType": "number",
                                                    "filter": {
                                                        "language": "kuery",
                                                        "query": "\"panw.system.cpu.system\": *"
                                                    },
                                                    "isBucketed": false,
                                                    "label": "System",
                                                    "operationType": "last_value",
                                                    "params": {
                                                        "sortField": "@timestamp"
                                                    },
                                                    "scale": "ratio",
                                                    "sourceField": "panw.system.cpu.system"
                                                },
                                                "f7a662cc-3b57-49cf-9dad-f72d1d79fd64": {
                                                    "customLabel": true,
                                                    "dataType": "number",
                                                    "filter": {
                                                        "language": "kuery",
                                                        "query": "\"panw.system.cpu.steal\": *"
                                                    },
                                                    "isBucketed": false,
                                                    "label": "Steal",
                                                    "operationType": "last_value",
                                                    "params": {
                                                        "sortField": "@timestamp"
                                                    },
                                                    "scale": "ratio",
                                                    "sourceField": "panw.system.cpu.steal"
                                                }
                                            },
                                            "incompleteColumns": {},
                                            "sampling": 1
                                        }
                                    }
                                },
                                "indexpattern": {
                                    "layers": {}
                                },
                                "textBased": {
                                    "layers": {}
                                }
                            },
                            "filters": [],
                            "internalReferences": [],
                            "query": {
                                "language": "kuery",
                                "query": ""
                            },
                            "visualization": {
                                "columns": [
                                    {
                                        "columnId": "905a04aa-1710-4cb4-bf5a-d2b312177d55",
                                        "isTransposed": false
                                    },
                                    {
                                        "columnId": "deb6ef95-c478-4813-b0d9-69e4a25385d5",
                                        "isTransposed": false
                                    },
                                    {
                                        "columnId": "de5c6831-fb44-488c-a2d0-1c9168f51317",
                                        "isTransposed": false
                                    },
                                    {
                                        "columnId": "65c51155-3397-479c-ae16-1d5f92b497c9",
                                        "isTransposed": false
                                    },
                                    {
                                        "columnId": "437b6d5b-4b0a-466e-8d6b-02f5e7c6a146",
                                        "isTransposed": false
                                    },
                                    {
                                        "columnId": "8f8e0e79-3e25-4cba-abf7-a4887722b403",
                                        "isMetric": true,
                                        "isTransposed": false
                                    },
                                    {
                                        "columnId": "951b20c4-dd2b-4ec1-be9b-eff9a2c107e5",
                                        "isTransposed": false
                                    },
                                    {
                                        "columnId": "f7a662cc-3b57-49cf-9dad-f72d1d79fd64",
                                        "isTransposed": false
                                    }
                                ],
                                "layerId": "ef579182-b6a5-4392-a32e-2cc104fed1ef",
                                "layerType": "data"
                            }
                        },
                        "title": "",
                        "type": "lens",
                        "visualizationType": "lnsDatatable"
                    },
                    "enhancements": {}
                },
                "gridData": {
                    "h": 6,
                    "i": "e9979bc0-3d3a-4eef-80a5-9dc75a2a1501",
                    "w": 23,
                    "x": 11,
                    "y": 0
                },
                "panelIndex": "e9979bc0-3d3a-4eef-80a5-9dc75a2a1501",
                "title": "CPU",
                "type": "lens"
            },
            {
                "embeddableConfig": {
                    "attributes": {
                        "references": [
                            {
                                "id": "metrics-*",
                                "name": "indexpattern-datasource-layer-d518bbf9-bd15-4582-9a24-ef33e5ee5002",
                                "type": "index-pattern"
                            }
                        ],
                        "state": {
                            "adHocDataViews": {},
                            "datasourceStates": {
                                "formBased": {
                                    "layers": {
                                        "d518bbf9-bd15-4582-9a24-ef33e5ee5002": {
                                            "columnOrder": [
                                                "9602f473-59a3-443d-8c5a-ddd4672fa3b3"
                                            ],
                                            "columns": {
                                                "9602f473-59a3-443d-8c5a-ddd4672fa3b3": {
                                                    "customLabel": true,
                                                    "dataType": "boolean",
                                                    "filter": {
                                                        "language": "kuery",
                                                        "query": "panw.system.fan.alarm:true "
                                                    },
                                                    "isBucketed": false,
                                                    "label": "Alarm Count",
                                                    "operationType": "last_value",
                                                    "params": {
                                                        "sortField": "@timestamp"
                                                    },
                                                    "scale": "ratio",
                                                    "sourceField": "panw.system.fan.alarm"
                                                }
                                            },
                                            "incompleteColumns": {}
                                        }
                                    }
                                },
                                "indexpattern": {
                                    "layers": {}
                                },
                                "textBased": {
                                    "layers": {}
                                }
                            },
                            "filters": [],
                            "internalReferences": [],
                            "query": {
                                "language": "kuery",
                                "query": ""
                            },
                            "visualization": {
                                "accessor": "9602f473-59a3-443d-8c5a-ddd4672fa3b3",
                                "layerId": "d518bbf9-bd15-4582-9a24-ef33e5ee5002",
                                "layerType": "data"
                            }
                        },
                        "title": "",
                        "type": "lens",
                        "visualizationType": "lnsLegacyMetric"
                    },
                    "enhancements": {}
                },
                "gridData": {
                    "h": 6,
                    "i": "f5e1a80e-ffc0-4ede-bd24-87beb30f886f",
                    "w": 7,
                    "x": 34,
                    "y": 0
                },
                "panelIndex": "f5e1a80e-ffc0-4ede-bd24-87beb30f886f",
                "title": "Fan Alarms",
                "type": "lens"
            },
            {
                "embeddableConfig": {
                    "attributes": {
                        "references": [
                            {
                                "id": "metrics-*",
                                "name": "indexpattern-datasource-layer-d518bbf9-bd15-4582-9a24-ef33e5ee5002",
                                "type": "index-pattern"
                            }
                        ],
                        "state": {
                            "adHocDataViews": {},
                            "datasourceStates": {
                                "formBased": {
                                    "layers": {
                                        "d518bbf9-bd15-4582-9a24-ef33e5ee5002": {
                                            "columnOrder": [
                                                "9602f473-59a3-443d-8c5a-ddd4672fa3b3"
                                            ],
                                            "columns": {
                                                "9602f473-59a3-443d-8c5a-ddd4672fa3b3": {
                                                    "customLabel": true,
                                                    "dataType": "number",
                                                    "filter": {
                                                        "language": "kuery",
                                                        "query": "panw.system.fan.alarm:true "
                                                    },
                                                    "isBucketed": false,
                                                    "label": "Alarm Count",
                                                    "operationType": "unique_count",
                                                    "params": {
                                                        "emptyAsNull": true
                                                    },
                                                    "scale": "ratio",
                                                    "sourceField": "panw.system.power.alarm"
                                                }
                                            },
                                            "incompleteColumns": {}
                                        }
                                    }
                                },
                                "indexpattern": {
                                    "layers": {}
                                },
                                "textBased": {
                                    "layers": {}
                                }
                            },
                            "filters": [],
                            "internalReferences": [],
                            "query": {
                                "language": "kuery",
                                "query": ""
                            },
                            "visualization": {
                                "accessor": "9602f473-59a3-443d-8c5a-ddd4672fa3b3",
                                "layerId": "d518bbf9-bd15-4582-9a24-ef33e5ee5002",
                                "layerType": "data"
                            }
                        },
                        "title": "",
                        "type": "lens",
                        "visualizationType": "lnsLegacyMetric"
                    },
                    "enhancements": {}
                },
                "gridData": {
                    "h": 6,
                    "i": "c63b417d-7b03-432d-ba25-c7c2effda1d4",
                    "w": 7,
                    "x": 41,
                    "y": 0
                },
                "panelIndex": "c63b417d-7b03-432d-ba25-c7c2effda1d4",
                "title": "Power Alarms",
                "type": "lens"
            },
            {
                "embeddableConfig": {
                    "attributes": {
                        "references": [
                            {
                                "id": "metrics-*",
                                "name": "indexpattern-datasource-layer-28c3773b-a896-466c-8a93-412deeb3313d",
                                "type": "index-pattern"
                            }
                        ],
                        "state": {
                            "adHocDataViews": {},
                            "datasourceStates": {
                                "formBased": {
                                    "layers": {
                                        "28c3773b-a896-466c-8a93-412deeb3313d": {
                                            "columnOrder": [
                                                "c7e7355e-e81d-465c-abcb-3344e49c9366",
                                                "0a0e84ce-cd78-46c5-be35-733b4af304ff",
                                                "d757c3e9-593a-4f46-8df3-a004b522701d",
                                                "a1334703-ed06-4934-8e4b-94028c12e490",
                                                "ad8cb1f6-3e19-4446-9df8-f3c1ba8912b2",
                                                "2dd79849-48ba-42d4-81c4-34dfe4427826"
                                            ],
                                            "columns": {
                                                "0a0e84ce-cd78-46c5-be35-733b4af304ff": {
                                                    "customLabel": true,
                                                    "dataType": "string",
                                                    "isBucketed": true,
                                                    "label": "Mounted",
                                                    "operationType": "terms",
                                                    "params": {
                                                        "exclude": [],
                                                        "excludeIsRegex": false,
                                                        "include": [],
                                                        "includeIsRegex": false,
                                                        "missingBucket": false,
                                                        "orderBy": {
                                                            "columnId": "d757c3e9-593a-4f46-8df3-a004b522701d",
                                                            "type": "column"
                                                        },
                                                        "orderDirection": "desc",
                                                        "otherBucket": true,
                                                        "parentFormat": {
                                                            "id": "terms"
                                                        },
                                                        "size": 5
                                                    },
                                                    "scale": "ordinal",
                                                    "sourceField": "panw.system.filesystem.mounted"
                                                },
                                                "2dd79849-48ba-42d4-81c4-34dfe4427826": {
                                                    "customLabel": true,
                                                    "dataType": "number",
                                                    "filter": {
                                                        "language": "kuery",
                                                        "query": "\"panw.system.filesystem.use_percent\": *"
                                                    },
                                                    "isBucketed": false,
                                                    "label": "Percent Used",
                                                    "operationType": "last_value",
                                                    "params": {
                                                        "format": {
                                                            "id": "number",
                                                            "params": {
                                                                "decimals": 0
                                                            }
                                                        },
                                                        "sortField": "@timestamp"
                                                    },
                                                    "scale": "ratio",
                                                    "sourceField": "panw.system.filesystem.use_percent"
                                                },
                                                "a1334703-ed06-4934-8e4b-94028c12e490": {
                                                    "customLabel": true,
                                                    "dataType": "number",
                                                    "filter": {
                                                        "language": "kuery",
                                                        "query": "\"panw.system.filesystem.used\": *"
                                                    },
                                                    "isBucketed": false,
                                                    "label": "Used",
                                                    "operationType": "last_value",
                                                    "params": {
                                                        "format": {
                                                            "id": "bytes",
                                                            "params": {
                                                                "decimals": 1
                                                            }
                                                        },
                                                        "sortField": "@timestamp"
                                                    },
                                                    "scale": "ratio",
                                                    "sourceField": "panw.system.filesystem.used"
                                                },
                                                "ad8cb1f6-3e19-4446-9df8-f3c1ba8912b2": {
                                                    "customLabel": true,
                                                    "dataType": "number",
                                                    "filter": {
                                                        "language": "kuery",
                                                        "query": "\"panw.system.filesystem.available\": *"
                                                    },
                                                    "isBucketed": false,
                                                    "label": "Available",
                                                    "operationType": "last_value",
                                                    "params": {
                                                        "format": {
                                                            "id": "bytes",
                                                            "params": {
                                                                "decimals": 1
                                                            }
                                                        },
                                                        "sortField": "@timestamp"
                                                    },
                                                    "scale": "ratio",
                                                    "sourceField": "panw.system.filesystem.available"
                                                },
                                                "c7e7355e-e81d-465c-abcb-3344e49c9366": {
                                                    "customLabel": true,
                                                    "dataType": "string",
                                                    "isBucketed": true,
                                                    "label": "Filesystem",
                                                    "operationType": "terms",
                                                    "params": {
                                                        "exclude": [],
                                                        "excludeIsRegex": false,
                                                        "include": [],
                                                        "includeIsRegex": false,
                                                        "missingBucket": false,
                                                        "orderAgg": {
                                                            "dataType": "number",
                                                            "isBucketed": false,
                                                            "label": "Maximum of oracle.tablespace.data_file.size.free.bytes",
                                                            "operationType": "max",
                                                            "params": {
                                                                "emptyAsNull": true
                                                            },
                                                            "scale": "ratio",
                                                            "sourceField": "oracle.tablespace.data_file.size.free.bytes"
                                                        },
                                                        "orderBy": {
                                                            "type": "custom"
                                                        },
                                                        "orderDirection": "desc",
                                                        "otherBucket": true,
                                                        "parentFormat": {
                                                            "id": "terms"
                                                        },
                                                        "size": 5
                                                    },
                                                    "scale": "ordinal",
                                                    "sourceField": "panw.system.filesystem.name"
                                                },
                                                "d757c3e9-593a-4f46-8df3-a004b522701d": {
                                                    "customLabel": true,
                                                    "dataType": "number",
                                                    "filter": {
                                                        "language": "kuery",
                                                        "query": "\"panw.system.filesystem.size\": *"
                                                    },
                                                    "isBucketed": false,
                                                    "label": "Filesystem Size",
                                                    "operationType": "last_value",
                                                    "params": {
                                                        "format": {
                                                            "id": "bytes",
                                                            "params": {
                                                                "decimals": 1
                                                            }
                                                        },
                                                        "sortField": "@timestamp"
                                                    },
                                                    "scale": "ratio",
                                                    "sourceField": "panw.system.filesystem.size"
                                                }
                                            },
                                            "incompleteColumns": {},
                                            "sampling": 1
                                        }
                                    }
                                },
                                "indexpattern": {
                                    "layers": {}
                                },
                                "textBased": {
                                    "layers": {}
                                }
                            },
                            "filters": [],
                            "internalReferences": [],
                            "query": {
                                "language": "kuery",
                                "query": ""
                            },
                            "visualization": {
                                "columns": [
                                    {
                                        "columnId": "c7e7355e-e81d-465c-abcb-3344e49c9366",
                                        "isTransposed": false
                                    },
                                    {
                                        "columnId": "0a0e84ce-cd78-46c5-be35-733b4af304ff",
                                        "isTransposed": false
                                    },
                                    {
                                        "columnId": "d757c3e9-593a-4f46-8df3-a004b522701d",
                                        "isTransposed": false,
                                        "width": 142
                                    },
                                    {
                                        "columnId": "a1334703-ed06-4934-8e4b-94028c12e490",
                                        "isTransposed": false,
                                        "width": 123.6
                                    },
                                    {
                                        "columnId": "ad8cb1f6-3e19-4446-9df8-f3c1ba8912b2",
                                        "isTransposed": false,
                                        "width": 124.1
                                    },
                                    {
                                        "columnId": "2dd79849-48ba-42d4-81c4-34dfe4427826",
                                        "hidden": false,
                                        "isTransposed": false
                                    }
                                ],
                                "layerId": "28c3773b-a896-466c-8a93-412deeb3313d",
                                "layerType": "data"
                            }
                        },
                        "title": "",
                        "type": "lens",
                        "visualizationType": "lnsDatatable"
                    },
                    "enhancements": {}
                },
                "gridData": {
                    "h": 15,
                    "i": "bbde7c83-0b1d-4c2f-8baf-12b15785d30b",
                    "w": 24,
                    "x": 0,
                    "y": 6
                },
                "panelIndex": "bbde7c83-0b1d-4c2f-8baf-12b15785d30b",
                "title": "Disk Usage",
                "type": "lens"
            },
            {
                "embeddableConfig": {
                    "attributes": {
                        "references": [
                            {
                                "id": "metrics-*",
                                "name": "indexpattern-datasource-layer-93308fd4-919e-470f-94cd-e05e7d89f7f7",
                                "type": "index-pattern"
                            },
                            {
                                "id": "metrics-*",
                                "name": "indexpattern-datasource-layer-ed5168bf-932a-4c12-9d93-3cbbcff1de60",
                                "type": "index-pattern"
                            }
                        ],
                        "state": {
                            "adHocDataViews": {},
                            "datasourceStates": {
                                "formBased": {
                                    "layers": {
                                        "93308fd4-919e-470f-94cd-e05e7d89f7f7": {
                                            "columnOrder": [
                                                "311360c1-eb5c-436c-9553-8f6aadc91ea5",
                                                "54ba8425-cf85-4a41-bc14-eb717409f9d4",
                                                "9156b77d-c585-4cfc-b23a-baa727bebfbd",
                                                "72cd3b18-27a6-4a62-a650-bbe5f09cbac5"
                                            ],
                                            "columns": {
                                                "311360c1-eb5c-436c-9553-8f6aadc91ea5": {
                                                    "dataType": "date",
                                                    "isBucketed": true,
                                                    "label": "@timestamp",
                                                    "operationType": "date_histogram",
                                                    "params": {
                                                        "dropPartials": false,
                                                        "includeEmptyRows": true,
                                                        "interval": "m"
                                                    },
                                                    "scale": "interval",
                                                    "sourceField": "@timestamp"
                                                },
                                                "54ba8425-cf85-4a41-bc14-eb717409f9d4": {
                                                    "customLabel": true,
                                                    "dataType": "number",
                                                    "filter": {
                                                        "language": "kuery",
                                                        "query": "\"panw.system.memory.buffer_cache\": *"
                                                    },
                                                    "isBucketed": false,
                                                    "label": "BufferCache",
                                                    "operationType": "last_value",
                                                    "params": {
                                                        "format": {
                                                            "id": "bytes",
                                                            "params": {
                                                                "decimals": 2
                                                            }
                                                        },
                                                        "sortField": "@timestamp"
                                                    },
                                                    "scale": "ratio",
                                                    "sourceField": "panw.system.memory.buffer_cache"
                                                },
                                                "72cd3b18-27a6-4a62-a650-bbe5f09cbac5": {
                                                    "customLabel": true,
                                                    "dataType": "number",
                                                    "filter": {
                                                        "language": "kuery",
                                                        "query": "\"panw.system.memory.free\": *"
                                                    },
                                                    "isBucketed": false,
                                                    "label": "Free",
                                                    "operationType": "last_value",
                                                    "params": {
                                                        "format": {
                                                            "id": "bytes",
                                                            "params": {
                                                                "decimals": 0
                                                            }
                                                        },
                                                        "sortField": "@timestamp"
                                                    },
                                                    "scale": "ratio",
                                                    "sourceField": "panw.system.memory.free"
                                                },
                                                "9156b77d-c585-4cfc-b23a-baa727bebfbd": {
                                                    "customLabel": true,
                                                    "dataType": "number",
                                                    "filter": {
                                                        "language": "kuery",
                                                        "query": "\"panw.system.memory.used\": *"
                                                    },
                                                    "isBucketed": false,
                                                    "label": "Used",
                                                    "operationType": "last_value",
                                                    "params": {
                                                        "format": {
                                                            "id": "bytes",
                                                            "params": {
                                                                "decimals": 0
                                                            }
                                                        },
                                                        "sortField": "@timestamp"
                                                    },
                                                    "scale": "ratio",
                                                    "sourceField": "panw.system.memory.used"
                                                }
                                            },
                                            "ignoreGlobalFilters": false,
                                            "incompleteColumns": {},
                                            "sampling": 1
                                        },
                                        "ed5168bf-932a-4c12-9d93-3cbbcff1de60": {
                                            "columnOrder": [
                                                "610f362a-3ad7-482a-b513-8259accdea4e"
                                            ],
                                            "columns": {
                                                "610f362a-3ad7-482a-b513-8259accdea4e": {
                                                    "customLabel": true,
                                                    "dataType": "number",
                                                    "filter": {
                                                        "language": "kuery",
                                                        "query": "\"panw.system.memory.total\": *"
                                                    },
                                                    "isBucketed": false,
                                                    "label": "TotalMemory",
                                                    "operationType": "last_value",
                                                    "params": {
                                                        "format": {
                                                            "id": "bytes",
                                                            "params": {
                                                                "decimals": 2
                                                            }
                                                        },
                                                        "sortField": "@timestamp"
                                                    },
                                                    "scale": "ratio",
                                                    "sourceField": "panw.system.memory.total"
                                                }
                                            },
                                            "ignoreGlobalFilters": false,
                                            "incompleteColumns": {},
                                            "linkToLayers": [],
                                            "sampling": 1
                                        }
                                    }
                                },
                                "indexpattern": {
                                    "layers": {}
                                },
                                "textBased": {
                                    "layers": {}
                                }
                            },
                            "filters": [],
                            "internalReferences": [],
                            "query": {
                                "language": "kuery",
                                "query": ""
                            },
                            "visualization": {
                                "axisTitlesVisibilitySettings": {
                                    "x": true,
                                    "yLeft": true,
                                    "yRight": true
                                },
                                "fittingFunction": "None",
                                "gridlinesVisibilitySettings": {
                                    "x": true,
                                    "yLeft": true,
                                    "yRight": true
                                },
                                "labelsOrientation": {
                                    "x": 0,
                                    "yLeft": 0,
                                    "yRight": 0
                                },
                                "layers": [
                                    {
                                        "accessors": [
                                            "72cd3b18-27a6-4a62-a650-bbe5f09cbac5",
                                            "54ba8425-cf85-4a41-bc14-eb717409f9d4",
                                            "9156b77d-c585-4cfc-b23a-baa727bebfbd"
                                        ],
                                        "colorMapping": {
                                            "assignments": [],
                                            "colorMode": {
                                                "type": "categorical"
                                            },
                                            "paletteId": "eui_amsterdam_color_blind",
                                            "specialAssignments": [
                                                {
                                                    "color": {
                                                        "type": "loop"
                                                    },
                                                    "rule": {
                                                        "type": "other"
                                                    },
                                                    "touched": false
                                                }
                                            ]
                                        },
                                        "layerId": "93308fd4-919e-470f-94cd-e05e7d89f7f7",
                                        "layerType": "data",
                                        "position": "top",
                                        "seriesType": "bar_stacked",
                                        "showGridlines": false,
                                        "xAccessor": "311360c1-eb5c-436c-9553-8f6aadc91ea5"
                                    },
                                    {
                                        "accessors": [
                                            "610f362a-3ad7-482a-b513-8259accdea4e"
                                        ],
                                        "layerId": "ed5168bf-932a-4c12-9d93-3cbbcff1de60",
                                        "layerType": "referenceLine",
                                        "yConfig": [
                                            {
                                                "axisMode": "left",
                                                "forAccessor": "610f362a-3ad7-482a-b513-8259accdea4e",
                                                "icon": "asterisk",
                                                "iconPosition": "left",
                                                "textVisibility": true
                                            }
                                        ]
                                    }
                                ],
                                "legend": {
                                    "isVisible": true,
                                    "position": "right"
                                },
                                "preferredSeriesType": "bar_stacked",
                                "tickLabelsVisibilitySettings": {
                                    "x": true,
                                    "yLeft": true,
                                    "yRight": true
                                },
                                "valueLabels": "hide"
                            }
                        },
                        "title": "",
                        "type": "lens",
                        "visualizationType": "lnsXY"
                    },
                    "enhancements": {}
                },
                "gridData": {
                    "h": 15,
                    "i": "cf3ac26c-5e4f-453d-937d-e345270a8a61",
                    "w": 24,
                    "x": 24,
                    "y": 6
                },
                "panelIndex": "cf3ac26c-5e4f-453d-937d-e345270a8a61",
                "title": "Memory",
                "type": "lens"
            },
            {
                "embeddableConfig": {
                    "attributes": {
                        "references": [
                            {
                                "id": "metrics-*",
                                "name": "indexpattern-datasource-layer-36de673c-5822-45a3-8465-9ea14d9bdba8",
                                "type": "index-pattern"
                            }
                        ],
                        "state": {
                            "adHocDataViews": {},
                            "datasourceStates": {
                                "formBased": {
                                    "layers": {
                                        "36de673c-5822-45a3-8465-9ea14d9bdba8": {
                                            "columnOrder": [
                                                "7e6e5ee1-4eea-4c3f-ae4b-c93b9b649b2b",
                                                "a7488650-e737-43c4-abad-3e6fc791303e",
                                                "ecdaca56-827c-4c4b-9dc0-56b5d331a2b6",
                                                "0939b98f-d573-4951-aed0-a85303e19855",
                                                "d5074c95-04ef-4640-90d3-903a5b81f256",
                                                "47e76e1e-7945-4185-941e-dfb453f88d64",
                                                "06880a20-0051-4812-9198-73759ba3240e"
                                            ],
                                            "columns": {
                                                "06880a20-0051-4812-9198-73759ba3240e": {
                                                    "dataType": "number",
                                                    "isBucketed": false,
                                                    "label": "Count of records",
                                                    "operationType": "count",
                                                    "params": {
                                                        "emptyAsNull": true
                                                    },
                                                    "scale": "ratio",
                                                    "sourceField": "___records___"
                                                },
                                                "0939b98f-d573-4951-aed0-a85303e19855": {
                                                    "customLabel": true,
                                                    "dataType": "string",
                                                    "isBucketed": true,
                                                    "label": "Date Issued",
                                                    "operationType": "terms",
                                                    "params": {
                                                        "exclude": [],
                                                        "excludeIsRegex": false,
                                                        "include": [],
                                                        "includeIsRegex": false,
                                                        "missingBucket": false,
                                                        "orderBy": {
                                                            "fallback": false,
                                                            "type": "alphabetical"
                                                        },
                                                        "orderDirection": "asc",
                                                        "otherBucket": true,
                                                        "parentFormat": {
                                                            "id": "terms"
                                                        },
                                                        "size": 20
                                                    },
                                                    "scale": "ordinal",
                                                    "sourceField": "panw.system.license.issued"
                                                },
                                                "47e76e1e-7945-4185-941e-dfb453f88d64": {
                                                    "customLabel": true,
                                                    "dataType": "boolean",
                                                    "isBucketed": true,
                                                    "label": "Expired",
                                                    "operationType": "terms",
                                                    "params": {
                                                        "exclude": [],
                                                        "excludeIsRegex": false,
                                                        "include": [],
                                                        "includeIsRegex": false,
                                                        "missingBucket": false,
                                                        "orderBy": {
                                                            "columnId": "06880a20-0051-4812-9198-73759ba3240e",
                                                            "type": "column"
                                                        },
                                                        "orderDirection": "desc",
                                                        "otherBucket": true,
                                                        "parentFormat": {
                                                            "id": "terms"
                                                        },
                                                        "size": 20
                                                    },
                                                    "scale": "ordinal",
                                                    "sourceField": "panw.system.license.expired"
                                                },
                                                "7e6e5ee1-4eea-4c3f-ae4b-c93b9b649b2b": {
                                                    "customLabel": true,
                                                    "dataType": "string",
                                                    "isBucketed": true,
                                                    "label": "Feature",
                                                    "operationType": "terms",
                                                    "params": {
                                                        "exclude": [],
                                                        "excludeIsRegex": false,
                                                        "include": [],
                                                        "includeIsRegex": false,
                                                        "missingBucket": false,
                                                        "orderBy": {
                                                            "fallback": false,
                                                            "type": "alphabetical"
                                                        },
                                                        "orderDirection": "asc",
                                                        "otherBucket": false,
                                                        "parentFormat": {
                                                            "id": "terms"
                                                        },
                                                        "size": 20
                                                    },
                                                    "scale": "ordinal",
                                                    "sourceField": "panw.system.license.feature"
                                                },
                                                "a7488650-e737-43c4-abad-3e6fc791303e": {
                                                    "customLabel": true,
                                                    "dataType": "string",
                                                    "isBucketed": true,
                                                    "label": "Description",
                                                    "operationType": "terms",
                                                    "params": {
                                                        "exclude": [],
                                                        "excludeIsRegex": false,
                                                        "include": [],
                                                        "includeIsRegex": false,
                                                        "missingBucket": false,
                                                        "orderBy": {
                                                            "columnId": "06880a20-0051-4812-9198-73759ba3240e",
                                                            "type": "column"
                                                        },
                                                        "orderDirection": "desc",
                                                        "otherBucket": true,
                                                        "parentFormat": {
                                                            "id": "terms"
                                                        },
                                                        "size": 20
                                                    },
                                                    "scale": "ordinal",
                                                    "sourceField": "panw.system.license.description"
                                                },
                                                "d5074c95-04ef-4640-90d3-903a5b81f256": {
                                                    "customLabel": true,
                                                    "dataType": "boolean",
                                                    "isBucketed": true,
                                                    "label": "Never Expires",
                                                    "operationType": "terms",
                                                    "params": {
                                                        "exclude": [],
                                                        "excludeIsRegex": false,
                                                        "include": [],
                                                        "includeIsRegex": false,
                                                        "missingBucket": false,
                                                        "orderBy": {
                                                            "columnId": "06880a20-0051-4812-9198-73759ba3240e",
                                                            "type": "column"
                                                        },
                                                        "orderDirection": "desc",
                                                        "otherBucket": true,
                                                        "parentFormat": {
                                                            "id": "terms"
                                                        },
                                                        "size": 20
                                                    },
                                                    "scale": "ordinal",
                                                    "sourceField": "panw.system.license.never_expires"
                                                },
                                                "ecdaca56-827c-4c4b-9dc0-56b5d331a2b6": {
                                                    "customLabel": true,
                                                    "dataType": "string",
                                                    "isBucketed": true,
                                                    "label": "Date Expires",
                                                    "operationType": "terms",
                                                    "params": {
                                                        "exclude": [],
                                                        "excludeIsRegex": false,
                                                        "include": [],
                                                        "includeIsRegex": false,
                                                        "missingBucket": false,
                                                        "orderBy": {
                                                            "columnId": "06880a20-0051-4812-9198-73759ba3240e",
                                                            "type": "column"
                                                        },
                                                        "orderDirection": "desc",
                                                        "otherBucket": true,
                                                        "parentFormat": {
                                                            "id": "terms"
                                                        },
                                                        "size": 20
                                                    },
                                                    "scale": "ordinal",
                                                    "sourceField": "panw.system.license.expires"
                                                }
                                            },
                                            "incompleteColumns": {},
                                            "sampling": 1
                                        }
                                    }
                                },
                                "indexpattern": {
                                    "layers": {}
                                },
                                "textBased": {
                                    "layers": {}
                                }
                            },
                            "filters": [],
                            "internalReferences": [],
                            "query": {
                                "language": "kuery",
                                "query": ""
                            },
                            "visualization": {
                                "columns": [
                                    {
                                        "columnId": "7e6e5ee1-4eea-4c3f-ae4b-c93b9b649b2b",
                                        "isTransposed": false,
                                        "width": 176.57142857142858
                                    },
                                    {
                                        "columnId": "0939b98f-d573-4951-aed0-a85303e19855",
                                        "isMetric": false,
                                        "isTransposed": false,
                                        "width": 199.57142857142858
                                    },
                                    {
                                        "columnId": "d5074c95-04ef-4640-90d3-903a5b81f256",
                                        "isTransposed": false
                                    },
                                    {
                                        "columnId": "47e76e1e-7945-4185-941e-dfb453f88d64",
                                        "isTransposed": false
                                    },
                                    {
                                        "columnId": "a7488650-e737-43c4-abad-3e6fc791303e",
                                        "isTransposed": false
                                    },
                                    {
                                        "columnId": "ecdaca56-827c-4c4b-9dc0-56b5d331a2b6",
                                        "isTransposed": false
                                    },
                                    {
                                        "columnId": "06880a20-0051-4812-9198-73759ba3240e",
                                        "isMetric": true,
                                        "isTransposed": false
                                    }
                                ],
                                "layerId": "36de673c-5822-45a3-8465-9ea14d9bdba8",
                                "layerType": "data"
                            }
                        },
                        "title": "",
                        "type": "lens",
                        "visualizationType": "lnsDatatable"
                    },
                    "enhancements": {}
                },
                "gridData": {
                    "h": 12,
                    "i": "5b0ea34a-9df4-4f4b-a589-bbd6aa08438f",
                    "w": 48,
                    "x": 0,
                    "y": 21
                },
                "panelIndex": "5b0ea34a-9df4-4f4b-a589-bbd6aa08438f",
                "title": "LIcenses",
                "type": "lens"
            }
        ],
        "timeRestore": false,
        "title": "PANW System Resources (Detail)",
        "version": 2
    },
    "coreMigrationVersion": "8.8.0",
    "created_at": "2024-09-26T22:02:07.958Z",
    "created_by": "u_mGBROF_q5bmFCATbLXAcCwKa0k8JvONAwSruelyKA5E_0",
    "id": "panw_metrics-323c0ebd-8b21-4a73-a969-511ef844434c",
    "managed": false,
    "references": [
        {
            "id": "metrics-*",
            "name": "kibanaSavedObjectMeta.searchSourceJSON.filter[0].meta.index",
            "type": "index-pattern"
        },
        {
            "id": "metrics-*",
            "name": "19dc313f-122c-4589-9cb4-f2ee8a306aeb:indexpattern-datasource-layer-84d94cdf-99fe-43f4-b520-8343a94355b6",
            "type": "index-pattern"
        },
        {
            "id": "metrics-*",
            "name": "e9979bc0-3d3a-4eef-80a5-9dc75a2a1501:indexpattern-datasource-layer-ef579182-b6a5-4392-a32e-2cc104fed1ef",
            "type": "index-pattern"
        },
        {
            "id": "metrics-*",
            "name": "f5e1a80e-ffc0-4ede-bd24-87beb30f886f:indexpattern-datasource-layer-d518bbf9-bd15-4582-9a24-ef33e5ee5002",
            "type": "index-pattern"
        },
        {
            "id": "metrics-*",
            "name": "c63b417d-7b03-432d-ba25-c7c2effda1d4:indexpattern-datasource-layer-d518bbf9-bd15-4582-9a24-ef33e5ee5002",
            "type": "index-pattern"
        },
        {
            "id": "metrics-*",
            "name": "bbde7c83-0b1d-4c2f-8baf-12b15785d30b:indexpattern-datasource-layer-28c3773b-a896-466c-8a93-412deeb3313d",
            "type": "index-pattern"
        },
        {
            "id": "metrics-*",
            "name": "cf3ac26c-5e4f-453d-937d-e345270a8a61:indexpattern-datasource-layer-93308fd4-919e-470f-94cd-e05e7d89f7f7",
            "type": "index-pattern"
        },
        {
            "id": "metrics-*",
            "name": "cf3ac26c-5e4f-453d-937d-e345270a8a61:indexpattern-datasource-layer-ed5168bf-932a-4c12-9d93-3cbbcff1de60",
            "type": "index-pattern"
        },
        {
            "id": "metrics-*",
            "name": "5b0ea34a-9df4-4f4b-a589-bbd6aa08438f:indexpattern-datasource-layer-36de673c-5822-45a3-8465-9ea14d9bdba8",
            "type": "index-pattern"
        },
        {
            "id": "metrics-*",
            "name": "controlGroup_b6299f3c-17e7-4663-8a63-3c856c683ea8:optionsListDataView",
            "type": "index-pattern"
        }
    ],
    "type": "dashboard",
    "typeMigrationVersion": "10.2.0",
    "updated_by": "u_mGBROF_q5bmFCATbLXAcCwKa0k8JvONAwSruelyKA5E_0"
}